{
  "generated_at": "2026-03-16T20:37:24.344326+09:00",
  "venue": "大村",
  "event_title": "夜の九州スポーツ杯",
  "date": "2026-02-14",
  "players": {
    "4545": {
      "name": "岡",
      "avg_st": 6.82,
      "count": 6
    },
    "5026": {
      "name": "安河内",
      "avg_st": 6.84,
      "count": 6
    },
    "4155": {
      "name": "長",
      "avg_st": 6.89,
      "count": 6
    },
    "4351": {
      "name": "里",
      "avg_st": 6.89,
      "count": 6
    },
    "3473": {
      "name": "石",
      "avg_st": 6.93,
      "count": 6
    },
    "4096": {
      "name": "石",
      "avg_st": 6.87,
      "count": 6
    },
    "4288": {
      "name": "永",
      "avg_st": 6.92,
      "count": 5
    },
    "4544": {
      "name": "松",
      "avg_st": 6.83,
      "count": 6
    },
    "4445": {
      "name": "宮",
      "avg_st": 6.79,
      "count": 6
    },
    "4102": {
      "name": "益",
      "avg_st": 6.88,
      "count": 6
    },
    "5142": {
      "name": "常",
      "avg_st": 6.85,
      "count": 6
    },
    "4530": {
      "name": "小",
      "avg_st": 6.81,
      "count": 6
    },
    "4294": {
      "name": "古",
      "avg_st": 6.91,
      "count": 5
    },
    "4256": {
      "name": "渡",
      "avg_st": 6.89,
      "count": 6
    },
    "4553": {
      "name": "坪",
      "avg_st": 6.86,
      "count": 5
    },
    "3783": {
      "name": "瓜",
      "avg_st": 6.83,
      "count": 6
    },
    "4079": {
      "name": "出",
      "avg_st": 6.86,
      "count": 6
    },
    "4566": {
      "name": "塩",
      "avg_st": 6.82,
      "count": 6
    },
    "4640": {
      "name": "山ノ内",
      "avg_st": 6.86,
      "count": 6
    },
    "4737": {
      "name": "竹",
      "avg_st": 6.88,
      "count": 6
    },
    "4320": {
      "name": "峰",
      "avg_st": 6.83,
      "count": 6
    },
    "4958": {
      "name": "溝",
      "avg_st": 6.81,
      "count": 5
    },
    "4522": {
      "name": "古",
      "avg_st": 6.92,
      "count": 5
    },
    "5084": {
      "name": "末",
      "avg_st": 6.85,
      "count": 6
    },
    "3898": {
      "name": "平",
      "avg_st": 6.84,
      "count": 5
    },
    "5028": {
      "name": "原",
      "avg_st": 6.84,
      "count": 6
    },
    "4736": {
      "name": "高",
      "avg_st": 6.92,
      "count": 5
    },
    "4848": {
      "name": "仲",
      "avg_st": 6.86,
      "count": 6
    },
    "4734": {
      "name": "安河内",
      "avg_st": 6.89,
      "count": 6
    },
    "4715": {
      "name": "村",
      "avg_st": 6.91,
      "count": 5
    },
    "4136": {
      "name": "江",
      "avg_st": 6.92,
      "count": 5
    },
    "4451": {
      "name": "松",
      "avg_st": 6.83,
      "count": 6
    },
    "4497": {
      "name": "桑",
      "avg_st": 6.9,
      "count": 5
    },
    "3257": {
      "name": "田",
      "avg_st": 6.94,
      "count": 2
    },
    "3623": {
      "name": "深",
      "avg_st": 6.91,
      "count": 5
    },
    "4932": {
      "name": "新",
      "avg_st": 6.89,
      "count": 6
    },
    "4287": {
      "name": "今",
      "avg_st": 6.9,
      "count": 5
    },
    "4296": {
      "name": "岡",
      "avg_st": 6.92,
      "count": 4
    },
    "4499": {
      "name": "滝",
      "avg_st": 6.89,
      "count": 6
    },
    "4433": {
      "name": "川",
      "avg_st": 6.87,
      "count": 5
    },
    "4174": {
      "name": "赤",
      "avg_st": 6.9,
      "count": 6
    },
    "4072": {
      "name": "森",
      "avg_st": 6.81,
      "count": 5
    },
    "4364": {
      "name": "池",
      "avg_st": 6.93,
      "count": 6
    },
    "4122": {
      "name": "安",
      "avg_st": 6.95,
      "count": 5
    },
    "4477": {
      "name": "篠",
      "avg_st": 6.93,
      "count": 6
    },
    "4831": {
      "name": "羽",
      "avg_st": 6.89,
      "count": 5
    },
    "3779": {
      "name": "原",
      "avg_st": 6.84,
      "count": 6
    },
    "4352": {
      "name": "下",
      "avg_st": 6.89,
      "count": 5
    },
    "5121": {
      "name": "定",
      "avg_st": 6.83,
      "count": 6
    },
    "4590": {
      "name": "渡",
      "avg_st": 6.91,
      "count": 5
    },
    "4371": {
      "name": "西",
      "avg_st": 6.91,
      "count": 6
    },
    "4350": {
      "name": "篠",
      "avg_st": 6.88,
      "count": 6
    }
  },
  "player_count": 52
}