{
  "generated_at": "2026-03-16T20:37:24.339560+09:00",
  "venue": "宮島",
  "event_title": "第６７回中国地区選手権",
  "date": "2026-02-12",
  "players": {
    "4798": {
      "name": "浜",
      "avg_st": 6.64,
      "count": 3
    },
    "3961": {
      "name": "谷",
      "avg_st": 6.75,
      "count": 3
    },
    "4434": {
      "name": "田",
      "avg_st": 6.67,
      "count": 3
    },
    "4537": {
      "name": "渡",
      "avg_st": 6.71,
      "count": 3
    },
    "4703": {
      "name": "森",
      "avg_st": 6.7,
      "count": 3
    },
    "4964": {
      "name": "土",
      "avg_st": 6.73,
      "count": 2
    },
    "4584": {
      "name": "村",
      "avg_st": 6.61,
      "count": 3
    },
    "3897": {
      "name": "白",
      "avg_st": 6.68,
      "count": 3
    },
    "4398": {
      "name": "船",
      "avg_st": 6.73,
      "count": 3
    },
    "4441": {
      "name": "末",
      "avg_st": 6.68,
      "count": 3
    },
    "4886": {
      "name": "入",
      "avg_st": 6.68,
      "count": 3
    },
    "4771": {
      "name": "下",
      "avg_st": 6.62,
      "count": 2
    },
    "4050": {
      "name": "田",
      "avg_st": 6.68,
      "count": 3
    },
    "4205": {
      "name": "山",
      "avg_st": 6.69,
      "count": 3
    },
    "3920": {
      "name": "正",
      "avg_st": 6.64,
      "count": 3
    },
    "4713": {
      "name": "白",
      "avg_st": 6.67,
      "count": 3
    },
    "4264": {
      "name": "長",
      "avg_st": 6.61,
      "count": 3
    },
    "4239": {
      "name": "竹",
      "avg_st": 6.66,
      "count": 3
    },
    "4482": {
      "name": "守",
      "avg_st": 6.74,
      "count": 3
    },
    "4842": {
      "name": "山",
      "avg_st": 6.65,
      "count": 3
    },
    "5145": {
      "name": "島",
      "avg_st": 6.64,
      "count": 2
    },
    "3024": {
      "name": "西",
      "avg_st": 6.78,
      "count": 3
    },
    "3942": {
      "name": "寺",
      "avg_st": 6.66,
      "count": 3
    },
    "4051": {
      "name": "清",
      "avg_st": 6.69,
      "count": 3
    },
    "4418": {
      "name": "茅",
      "avg_st": 6.64,
      "count": 3
    },
    "4600": {
      "name": "井",
      "avg_st": 6.63,
      "count": 3
    },
    "4361": {
      "name": "柳",
      "avg_st": 6.65,
      "count": 3
    },
    "4601": {
      "name": "森",
      "avg_st": 6.59,
      "count": 3
    },
    "4011": {
      "name": "堀之内",
      "avg_st": 6.61,
      "count": 2
    },
    "3618": {
      "name": "海",
      "avg_st": 6.7,
      "count": 3
    },
    "4762": {
      "name": "藤",
      "avg_st": 6.59,
      "count": 3
    },
    "4980": {
      "name": "佐々木",
      "avg_st": 6.66,
      "count": 3
    },
    "4069": {
      "name": "山",
      "avg_st": 6.63,
      "count": 3
    },
    "4324": {
      "name": "海",
      "avg_st": 6.59,
      "count": 3
    },
    "3737": {
      "name": "上",
      "avg_st": 6.76,
      "count": 3
    },
    "3717": {
      "name": "立",
      "avg_st": 6.7,
      "count": 3
    },
    "4682": {
      "name": "大",
      "avg_st": 6.68,
      "count": 3
    },
    "4292": {
      "name": "麻",
      "avg_st": 6.72,
      "count": 3
    },
    "4166": {
      "name": "吉",
      "avg_st": 6.68,
      "count": 3
    },
    "3435": {
      "name": "寺",
      "avg_st": 6.68,
      "count": 3
    },
    "4064": {
      "name": "原",
      "avg_st": 6.66,
      "count": 3
    },
    "4108": {
      "name": "吉",
      "avg_st": 6.66,
      "count": 2
    },
    "3874": {
      "name": "山",
      "avg_st": 6.63,
      "count": 3
    },
    "3300": {
      "name": "川",
      "avg_st": 6.74,
      "count": 3
    },
    "4302": {
      "name": "西",
      "avg_st": 6.63,
      "count": 3
    },
    "4475": {
      "name": "末",
      "avg_st": 6.62,
      "count": 2
    },
    "4163": {
      "name": "山",
      "avg_st": 6.67,
      "count": 1
    },
    "4985": {
      "name": "井",
      "avg_st": 6.66,
      "count": 3
    },
    "4089": {
      "name": "妹",
      "avg_st": 6.68,
      "count": 3
    },
    "4963": {
      "name": "實",
      "avg_st": 6.69,
      "count": 2
    },
    "3499": {
      "name": "市",
      "avg_st": 6.73,
      "count": 3
    }
  },
  "player_count": 51
}