{
  "generated_at": "2026-03-18T00:23:27.682004+09:00",
  "venue": "平和島",
  "event_title": "開設７０周年記念 トーキョー・ベイ・カップ",
  "date": "2025-03-16",
  "players": {
    "4757": {
      "name": "山 田 祐 也",
      "avg_st": 0.13,
      "count": 3
    },
    "4953": {
      "name": "尾 上 雅 也",
      "avg_st": 0.18,
      "count": 2
    },
    "4066": {
      "name": "東 本 勝 利",
      "avg_st": 0.08,
      "count": 2
    },
    "4524": {
      "name": "深 谷 知 博",
      "avg_st": 0.1,
      "count": 3
    },
    "4061": {
      "name": "萩 原 秀 人",
      "avg_st": 0.09,
      "count": 3
    },
    "4627": {
      "name": "藤 原 菜 希",
      "avg_st": 0.16,
      "count": 3
    },
    "3995": {
      "name": "重 野 哲 之",
      "avg_st": 0.14,
      "count": 3
    },
    "4075": {
      "name": "中 野 次 郎",
      "avg_st": 0.1,
      "count": 3
    },
    "4418": {
      "name": "茅 原 悠 紀",
      "avg_st": 0.1,
      "count": 3
    },
    "5226": {
      "name": "藤 田 俊 祐",
      "avg_st": 0.18,
      "count": 2
    },
    "4659": {
      "name": "木 下 翔 太",
      "avg_st": 0.13,
      "count": 3
    },
    "4546": {
      "name": "浜 田 亜理沙",
      "avg_st": 0.15,
      "count": 3
    },
    "4468": {
      "name": "大 池 佑 来",
      "avg_st": 0.16,
      "count": 3
    },
    "4686": {
      "name": "丸 野 一 樹",
      "avg_st": 0.15,
      "count": 3
    },
    "3388": {
      "name": "今 垣 光太郎",
      "avg_st": 0.13,
      "count": 3
    },
    "4444": {
      "name": "桐 生 順 平",
      "avg_st": 0.1,
      "count": 3
    },
    "4850": {
      "name": "野 中 一 平",
      "avg_st": 0.11,
      "count": 3
    },
    "4278": {
      "name": "藤 岡 俊 介",
      "avg_st": 0.17,
      "count": 3
    },
    "4446": {
      "name": "和 田 兼 輔",
      "avg_st": 0.11,
      "count": 3
    },
    "4537": {
      "name": "渡 邉 和 将",
      "avg_st": 0.09,
      "count": 3
    },
    "3716": {
      "name": "石 渡 鉄 兵",
      "avg_st": 0.07,
      "count": 3
    },
    "4847": {
      "name": "佐 藤 隆太郎",
      "avg_st": 0.15,
      "count": 3
    },
    "4428": {
      "name": "有 賀 達 也",
      "avg_st": 0.1,
      "count": 3
    },
    "4415": {
      "name": "下 出 卓 矢",
      "avg_st": 0.09,
      "count": 2
    },
    "4739": {
      "name": "中 村 晃 朋",
      "avg_st": 0.1,
      "count": 2
    },
    "4908": {
      "name": "上 田 龍 星",
      "avg_st": 0.11,
      "count": 3
    },
    "3854": {
      "name": "吉 川 元 浩",
      "avg_st": 0.13,
      "count": 3
    },
    "4685": {
      "name": "島 村 隆 幸",
      "avg_st": 0.13,
      "count": 3
    },
    "4544": {
      "name": "松 田 大志郎",
      "avg_st": 0.18,
      "count": 3
    },
    "4297": {
      "name": "山 田 哲 也",
      "avg_st": 0.13,
      "count": 3
    },
    "4477": {
      "name": "篠 崎 仁 志",
      "avg_st": 0.15,
      "count": 2
    },
    "4787": {
      "name": "椎 名 豊",
      "avg_st": 0.16,
      "count": 3
    },
    "4290": {
      "name": "稲 田 浩 二",
      "avg_st": 0.13,
      "count": 3
    },
    "4643": {
      "name": "近 江 翔 吾",
      "avg_st": 0.19,
      "count": 2
    },
    "4055": {
      "name": "吉 田 俊 彦",
      "avg_st": 0.14,
      "count": 3
    },
    "4759": {
      "name": "今 泉 友 吾",
      "avg_st": 0.11,
      "count": 3
    },
    "4308": {
      "name": "河 村 了",
      "avg_st": 0.19,
      "count": 3
    },
    "3909": {
      "name": "佐々木 康 幸",
      "avg_st": 0.12,
      "count": 3
    },
    "4743": {
      "name": "木 村 仁 紀",
      "avg_st": 0.13,
      "count": 2
    },
    "4748": {
      "name": "渡 邉 雄 朗",
      "avg_st": 0.1,
      "count": 3
    },
    "4926": {
      "name": "吉 川 貴 仁",
      "avg_st": 0.21,
      "count": 3
    },
    "4391": {
      "name": "松 田 祐 季",
      "avg_st": 0.17,
      "count": 3
    },
    "3874": {
      "name": "山 本 寛 久",
      "avg_st": 0.13,
      "count": 3
    },
    "4044": {
      "name": "湯 川 浩 司",
      "avg_st": 0.13,
      "count": 3
    },
    "3908": {
      "name": "重 成 一 人",
      "avg_st": 0.17,
      "count": 2
    },
    "4238": {
      "name": "毒 島 誠",
      "avg_st": 0.16,
      "count": 3
    },
    "4350": {
      "name": "篠 崎 元 志",
      "avg_st": 0.16,
      "count": 3
    },
    "3978": {
      "name": "齊 藤 仁",
      "avg_st": 0.15,
      "count": 3
    },
    "4502": {
      "name": "遠 藤 エ ミ",
      "avg_st": 0.2,
      "count": 3
    },
    "4719": {
      "name": "上 條 暢 嵩",
      "avg_st": 0.14,
      "count": 3
    },
    "4494": {
      "name": "河 合 佑 樹",
      "avg_st": 0.13,
      "count": 3
    }
  },
  "player_count": 51
}