{
  "generated_at": "2026-03-23T18:30:18.556110+09:00",
  "venue": "蒲郡",
  "event_title": "日本財団会長杯争奪戦",
  "date": "2023-03-29",
  "players": {
    "3922": {
      "name": "菅 沼 佳 昭",
      "avg_st": 0.18,
      "count": 3
    },
    "3621": {
      "name": "天 野 晶 夫",
      "avg_st": 0.14,
      "count": 3
    },
    "4402": {
      "name": "乙 藤 智 史",
      "avg_st": 0.15,
      "count": 3
    },
    "3742": {
      "name": "宮 地 秀 祈",
      "avg_st": 0.22,
      "count": 3
    },
    "3072": {
      "name": "西 田 靖",
      "avg_st": 0.21,
      "count": 3
    },
    "4920": {
      "name": "桐 村 翔 太",
      "avg_st": 0.16,
      "count": 3
    },
    "4377": {
      "name": "濱 本 優 一",
      "avg_st": 0.08,
      "count": 3
    },
    "4298": {
      "name": "宮 下 元 胤",
      "avg_st": 0.12,
      "count": 3
    },
    "4579": {
      "name": "中 嶋 健一郎",
      "avg_st": 0.2,
      "count": 4
    },
    "5190": {
      "name": "大 月 遊 雅",
      "avg_st": 0.16,
      "count": 3
    },
    "4906": {
      "name": "鈴 木 雅 希",
      "avg_st": 0.28,
      "count": 4
    },
    "4346": {
      "name": "前 田 健太郎",
      "avg_st": 0.15,
      "count": 3
    },
    "4537": {
      "name": "渡 邉 和 将",
      "avg_st": 0.12,
      "count": 2
    },
    "4960": {
      "name": "黒 野 元 基",
      "avg_st": 0.16,
      "count": 4
    },
    "4360": {
      "name": "庄 司 孝 輔",
      "avg_st": 0.18,
      "count": 4
    },
    "3843": {
      "name": "上 之 晃 弘",
      "avg_st": 0.16,
      "count": 3
    },
    "5023": {
      "name": "久 永 祥 平",
      "avg_st": 0.24,
      "count": 3
    },
    "4273": {
      "name": "佐 藤 旭",
      "avg_st": 0.19,
      "count": 4
    },
    "4431": {
      "name": "石 塚 裕 介",
      "avg_st": 0.17,
      "count": 3
    },
    "3717": {
      "name": "立 間 充 宏",
      "avg_st": 0.11,
      "count": 3
    },
    "4538": {
      "name": "笠 置 博 之",
      "avg_st": 0.12,
      "count": 3
    },
    "3448": {
      "name": "高 山 秀 雄",
      "avg_st": 0.12,
      "count": 3
    },
    "4626": {
      "name": "伊 藤 紘 章",
      "avg_st": 0.19,
      "count": 3
    },
    "4370": {
      "name": "山 口 達 也",
      "avg_st": 0.11,
      "count": 4
    },
    "4266": {
      "name": "長 田 頼 宗",
      "avg_st": 0.13,
      "count": 4
    },
    "3381": {
      "name": "滝 沢 芳 行",
      "avg_st": 0.12,
      "count": 3
    },
    "4531": {
      "name": "武 富 智 亮",
      "avg_st": 0.15,
      "count": 3
    },
    "4793": {
      "name": "金 子 萌",
      "avg_st": 0.19,
      "count": 3
    },
    "5181": {
      "name": "森 智 哉",
      "avg_st": 0.21,
      "count": 3
    },
    "4500": {
      "name": "山 田 康 二",
      "avg_st": 0.12,
      "count": 4
    },
    "4102": {
      "name": "益 田 啓 司",
      "avg_st": 0.08,
      "count": 3
    },
    "3656": {
      "name": "伯 母 芳 恒",
      "avg_st": 0.11,
      "count": 3
    },
    "3211": {
      "name": "北 川 敏 弘",
      "avg_st": 0.14,
      "count": 3
    },
    "4389": {
      "name": "伊 藤 喜 智",
      "avg_st": 0.19,
      "count": 3
    },
    "3752": {
      "name": "宇 土 泰 就",
      "avg_st": 0.18,
      "count": 3
    },
    "4796": {
      "name": "春 園 功 太",
      "avg_st": 0.07,
      "count": 3
    },
    "4364": {
      "name": "池 永 太",
      "avg_st": 0.12,
      "count": 4
    },
    "4293": {
      "name": "鈴 木 智 啓",
      "avg_st": 0.24,
      "count": 3
    },
    "4362": {
      "name": "土 屋 智 則",
      "avg_st": 0.15,
      "count": 4
    },
    "4676": {
      "name": "後 藤 隼 之",
      "avg_st": 0.17,
      "count": 3
    },
    "3406": {
      "name": "中 里 英 夫",
      "avg_st": 0.23,
      "count": 1
    },
    "3501": {
      "name": "川 上 昇 平",
      "avg_st": 0.15,
      "count": 3
    },
    "4230": {
      "name": "濱 崎 直 矢",
      "avg_st": 0.16,
      "count": 3
    },
    "4161": {
      "name": "黒 柳 浩 孝",
      "avg_st": 0.23,
      "count": 3
    },
    "4785": {
      "name": "木 幡 純 也",
      "avg_st": 0.17,
      "count": 3
    }
  },
  "player_count": 45
}